pyservos/__init__.py
pyservos/ax12.py
pyservos/bin/__init__.py
pyservos/bin/lib.py
pyservos/bin/servoAX12.py
pyservos/common.py
pyservos/debug.py
pyservos/pi_servo_serial.py
pyservos/protocol1.py
pyservos/protocol2.py
pyservos/servo_serial.py
pyservos/utils.py
pyservos/xl320.py
pyservos/xl430.py
pyservos-2.1.0.dist-info/entry_points.txt
pyservos-2.1.0.dist-info/WHEEL
pyservos-2.1.0.dist-info/METADATA
pyservos-2.1.0.dist-info/RECORD
