Metadata-Version: 2.1
Name: pyservos
Version: 2.1.0
Summary: Yet another dynamixel python driver
Home-page: https://pypi.org/project/pyservos/
License: MIT
Keywords: ax-12,ax12,xl430,xl320,dynamixel,servo,smart
Author: walchko
Author-email: walchko@users.noreply.github.com
Requires-Python: >=3.6
Classifier: Development Status :: 4 - Beta
Classifier: Intended Audience :: Developers
Classifier: License :: OSI Approved :: MIT License
Classifier: Operating System :: OS Independent
Classifier: Programming Language :: Python :: 3
Classifier: Programming Language :: Python :: 3.6
Classifier: Programming Language :: Python :: 3.7
Classifier: Programming Language :: Python :: 3.8
Classifier: Topic :: Software Development :: Libraries
Classifier: Topic :: Software Development :: Libraries :: Application Frameworks
Classifier: Topic :: Software Development :: Libraries :: Python Modules
Requires-Dist: colorama
Requires-Dist: importlib-metadata; python_version < "3.8"
Requires-Dist: pyserial
Project-URL: Repository, http://github.com/MultipedRobotics/pyservos
